<?xml version="1.0" encoding="utf-8" standalone="yes"?>
<!--
 * Copyright (C) 2022 The Android Open Source Project
 *
 * Licensed under the Apache License, Version 2.0 (the "License");
 * you may not use this file except in compliance with the License.
 * You may obtain a copy of the License at
 *
 *      http://www.apache.org/licenses/LICENSE-2.0
 *
 * Unless required by applicable law or agreed to in writing, software
 * distributed under the License is distributed on an "AS IS" BASIS,
 * WITHOUT WARRANTIES OR CONDITIONS OF ANY KIND, either express or implied.
 * See the License for the specific language governing permissions and
 * limitations under the License.
-->
<carrier_config>
    <!-- Ims General -->
    <boolean name="ims.allow_unknown_country_element_in_geolocation_pidf_bool" value="false"/>

    <!-- Aos -->
    <boolean name="ims.block_reg_on_cs_call_bool" value="false"/>
    <int-array name="ims.ims_identity_priority_int_array" num="1">
        <item value="1"/>
    </int-array>
    <int name="imswfc.registration_private_header_int" value="2"/>

    <!-- Ut/Xcap AOSP -->
    <boolean name="carrier_supports_ss_over_ut_bool" value="true"/>

    <int-array name="imsvoice.srvcc_type_int_array" num="1">
        <item value="0"/>
    </int-array>

    <!-- ImsMedia -->
    <pbundle name="imsvoice.audio_codec_capability_payload_types_bundle">
        <int-array name="imsvoice.evs_payload_type_int_array" num="1">
            <item value="103"/>
        </int-array>
        <int-array name="imsvoice.amrwb_payload_type_int_array" num="2">
            <item value="97"/>
            <item value="98"/>
        </int-array>
        <int-array name="imsvoice.amrnb_payload_type_int_array" num="2">
            <item value="99"/>
            <item value="100"/>
        </int-array>
        <int-array name="imsvoice.dtmfwb_payload_type_int_array" num="1">
            <item value="101"/>
        </int-array>
        <int-array name="imsvoice.dtmfnb_payload_type_int_array" num="1">
            <item value="102"/>
        </int-array>
    </pbundle>
    <pbundle name="imsvoice.evs_payload_description_bundle">
        <pbundle name="103">
            <int name="imsvoice.codec_attribute_cmr_int" value="-1"/>
            <int name="imsvoice.codec_attribute_mode_change_capability_int" value="2"/>
            <int name="imsvoice.evs_codec_attribute_bandwidth_int" value="5"/>
            <int-array name="imsvoice.evs_codec_attribute_bitrate_int_array" num="2">
                <item value="0"/>
                <item value="6"/>
            </int-array>
            <boolean name="imsvoice.evs_codec_attribute_dtx_bool" value="true"/>
            <boolean name="imsvoice.evs_codec_attribute_dtx_recv_bool" value="true"/>
        </pbundle>
    </pbundle>
    <pbundle name="imsvoice.amrwb_payload_description_bundle">
        <pbundle name="97">
            <int-array name="imsvoice.amr_codec_attribute_modeset_int_array" num="3">
                <item value="0"/>
                <item value="1"/>
                <item value="2"/>
            </int-array>
            <int name="imsvoice.amr_codec_attribute_payload_format_int" value="0"/>
            <int name="imsvoice.codec_attribute_mode_change_capability_int" value="2"/>
        </pbundle>
        <pbundle name="98">
            <int-array name="imsvoice.amr_codec_attribute_modeset_int_array" num="3">
                <item value="0"/>
                <item value="1"/>
                <item value="2"/>
            </int-array>
            <int name="imsvoice.amr_codec_attribute_payload_format_int" value="1"/>
            <int name="imsvoice.codec_attribute_mode_change_capability_int" value="2"/>
        </pbundle>
    </pbundle>
    <pbundle name="imsvoice.amrnb_payload_description_bundle">
        <pbundle name="99">
            <int-array name="imsvoice.amr_codec_attribute_modeset_int_array" num="3">
                <item value="0"/>
                <item value="1"/>
                <item value="2"/>
            </int-array>
            <int name="imsvoice.amr_codec_attribute_payload_format_int" value="0"/>
            <int name="imsvoice.codec_attribute_mode_change_capability_int" value="2"/>
        </pbundle>
        <pbundle name="100">
            <int-array name="imsvoice.amr_codec_attribute_modeset_int_array" num="3">
                <item value="0"/>
                <item value="1"/>
                <item value="2"/>
            </int-array>
            <int name="imsvoice.amr_codec_attribute_payload_format_int" value="1"/>
            <int name="imsvoice.codec_attribute_mode_change_capability_int" value="2"/>
        </pbundle>
    </pbundle>

    <!-- Audio -->
    <boolean name="imsvoice.audio_evs_support_bool" value="true"/>
    <boolean name="imsvoice.audio_bw_nego_option_bool" value="true"/>
    <int name="imsvoice.audio_rtp_dscp_int" value="46"/>
    <int-array name="imsvoice.audio_port_rtp_int_array" num="2">
        <item value="50010"/>
        <item value="50060"/>
    </int-array>
    <boolean name="imsvoice.audio_show_codec_attribute_modeset_bool" value="true"/>
    <int name="imsvoice.audio_as_bandwidth_kbps_int" value="49"/>
    <int name="imsvoice.audio_rs_bandwidth_bps_int" value="0"/>
    <int name="imsvoice.audio_rr_bandwidth_bps_int" value="2500"/>
    <int name="imsvoice.audio_rtp_inactivity_timer_millis_int" value="20000"/>
    <int name="imsvoice.audio_rtcp_inactivity_timer_millis_int" value="20000"/>
    <int-array name="imsvoice.audio_inactivity_call_end_reasons_int_array" num="3">
        <item value="0"/>
        <item value="2"/>
        <item value="4"/>
    </int-array>

    <int name="imsvoice.audio_telephone_event_duration_millis_int" value="200"/>

    <int name="imsvoice.audio_maxred_int" value="220"/>
    <boolean name="imsvoice.audio_show_codec_attribute_dtx_bool" value="false"/>
    <boolean name="imsvoice.audio_show_codec_attribute_amrwbio_modeset_bool" value="false"/>

</carrier_config>
