<?xml version="1.0" encoding="utf-8" standalone="yes"?>
<!--
 * Copyright (C) 2025 The Android Open Source Project
 *
 * Licensed under the Apache License, Version 2.0 (the "License");
 * you may not use this file except in compliance with the License.
 * You may obtain a copy of the License at
 *
 *      http://www.apache.org/licenses/LICENSE-2.0
 *
 * Unless required by applicable law or agreed to in writing, software
 * distributed under the License is distributed on an "AS IS" BASIS,
 * WITHOUT WARRANTIES OR CONDITIONS OF ANY KIND, either express or implied.
 * See the License for the specific language governing permissions and
 * limitations under the License.
-->
<carrier_config>
    <!-- Carrier configurations -->
    <!-- Mtc Assets -->
    <int name="imsvoice.policy_for_tcall_timer_expiry_of_volte_call_int" value="8"/>
    <int name="imswfc.policy_for_tcall_timer_expiry_of_vowifi_call_int" value="8"/>

    <!-- Media -->
    <int name="imsvoice.audio_maxred_int" value="0"/>
    <boolean name="imsvoice.audio_evs_support_bool" value="true"/>
    <boolean name="imsvoice.audio_bw_nego_option_bool" value="true"/>
    <int name="imsvoice.audio_ptime_millis_int" value="20"/>
    <int name="imsvoice.audio_maxptime_millis_int" value="240"/>
    <boolean name="imsvoice.audio_show_codec_attribute_modeset_bool" value="false"/>
    <boolean name="imsvoice.audio_show_codec_attribute_dtx_bool" value="false"/>
    <boolean name="imsvoice.audio_show_codec_attribute_amrwbio_modeset_bool" value="false"/>
    <int name="imsvoice.evs_amrwb_io_mode_set_int" value="7"/>
</carrier_config>
